<?xml version="1.0" encoding="UTF-8"?>
<definitions>
  <definition>
    <key>text_subject</key>
    <value><![CDATA[〜 - 〜訂購]]></value>
  </definition>
  <definition>
    <key>text_greeting</key>
    <value><![CDATA[感謝您〜產品的興趣。您的訂單已收到並確認付款後，將被處理。]]></value>
  </definition>
  <definition>
    <key>text_received</key>
    <value><![CDATA[您收到的訂單。]]></value>
  </definition>
  <definition>
    <key>text_order_detail</key>
    <value><![CDATA[訂單詳細信息]]></value>
  </definition>
  <definition>
    <key>text_order_id</key>
    <value><![CDATA[訂單ID：]]></value>
  </definition>
  <definition>
    <key>text_date_added</key>
    <value><![CDATA[有序日期：]]></value>
  </definition>
  <definition>
    <key>text_order_status</key>
    <value><![CDATA[訂單狀態：]]></value>
  </definition>
  <definition>
    <key>text_invoice</key>
    <value><![CDATA[要查看下面的鏈接您的訂單點擊：]]></value>
  </definition>
  <definition>
    <key>text_shipping_method</key>
    <value><![CDATA[郵寄方式：]]></value>
  </definition>
  <definition>
    <key>text_payment_method</key>
    <value><![CDATA[付款方法：]]></value>
  </definition>
  <definition>
    <key>text_shipping_address</key>
    <value><![CDATA[郵寄地址]]></value>
  </definition>
  <definition>
    <key>text_payment_address</key>
    <value><![CDATA[付款地址]]></value>
  </definition>
  <definition>
    <key>text_email</key>
    <value><![CDATA[電子郵件：]]></value>
  </definition>
  <definition>
    <key>text_telephone</key>
    <value><![CDATA[電話：]]></value>
  </definition>
  <definition>
    <key>text_mobile_phone</key>
    <value><![CDATA[移動電話：]]></value>
  </definition>
  <definition>
    <key>text_fax</key>
    <value><![CDATA[傳真：]]></value>
  </definition>
  <definition>
    <key>text_ip</key>
    <value><![CDATA[IP地址：]]></value>
  </definition>
  <definition>
    <key>text_product</key>
    <value><![CDATA[產品介紹：]]></value>
  </definition>
  <definition>
    <key>text_total</key>
    <value><![CDATA[總計：]]></value>
  </definition>
  <definition>
    <key>text_download</key>
    <value><![CDATA[一旦您的款項已被證實可以點擊下面的鏈接訪問您下載的產品：]]></value>
  </definition>
  <definition>
    <key>text_comment</key>
    <value><![CDATA[您的訂單的意見是：]]></value>
  </definition>
  <definition>
    <key>text_footer</key>
    <value><![CDATA[如果您有任何疑問，請回覆此郵件。]]></value>
  </definition>
  <definition>
    <key>text_powered_by</key>
    <value><![CDATA[供電]]></value>
  </definition>
  <definition>
    <key>text_new_order</key>
    <value><![CDATA[新命令 - ＃]]></value>
  </definition>
  <definition>
    <key>text_new_order_text</key>
    <value><![CDATA[客戶〜添加新秩序]]></value>
  </definition>
  <definition>
    <key>column_product</key>
    <value><![CDATA[產品]]></value>
  </definition>
  <definition>
    <key>column_model</key>
    <value><![CDATA[模型]]></value>
  </definition>
  <definition>
    <key>column_quantity</key>
    <value><![CDATA[數量]]></value>
  </definition>
  <definition>
    <key>column_price</key>
    <value><![CDATA[價錢]]></value>
  </definition>
  <definition>
    <key>column_total</key>
    <value><![CDATA[總]]></value>
  </definition>
</definitions>
