<?xml version="1.0" encoding="UTF-8"?>
<definitions>
  <definition>
    <key>im_text_notification</key>
    <value><![CDATA[Oznámení]]></value>
  </definition>
  <definition>
    <key>im_error_mail_address</key>
    <value><![CDATA[E-mailová adresa %s není platný!]]></value>
  </definition>
  <definition>
    <key>im_protocol_email_title</key>
    <value><![CDATA[E-mailem]]></value>
  </definition>
  <definition>
    <key>im_protocol_sms_title</key>
    <value><![CDATA[SMS]]></value>
  </definition>
  <definition>
    <key>im_protocol_sms_empty_warn</key>
    <value><![CDATA[Oznámení prostřednictvím SMS nejsou možné. Číslo mobilního telefonu není uložen ve svých záznamech účtu.]]></value>
  </definition>
  <definition>
    <key>im_sendpoint_name_order_update</key>
    <value><![CDATA[objednat Aktualizace]]></value>
  </definition>
  <definition>
    <key>im_sendpoint_name_order_update_note</key>
    <value><![CDATA[Zvolit, zda chcete přijímat oznámení o aktualizacích vašich objednávek.]]></value>
  </definition>
  <definition>
    <key>im_order_update_text_to_admin</key>
    <value><![CDATA[Objednat # %s byla aktualizována! Stav objednávky ID %s]]></value>
  </definition>
  <definition>
    <key>im_order_update_text_to_customer</key>
    <value><![CDATA[Vaše objednávka # %s Aktualizováno. New Order Status je %s]]></value>
  </definition>
  <definition>
    <key>im_new_order_text_to_admin</key>
    <value><![CDATA[New Order # %s byl kladen!]]></value>
  </definition>
  <definition>
    <key>im_new_customer_text_to_admin</key>
    <value><![CDATA[Nový zákazník # %s byla zaregistrována!]]></value>
  </definition>
  <definition>
    <key>im_new_subscriber_text_to_admin</key>
    <value><![CDATA[Nový Účastník # %s byla zaregistrována!]]></value>
  </definition>
  <definition>
    <key>im_sendpoint_name_customer_account_update</key>
    <value><![CDATA[Aktualizace účtu]]></value>
  </definition>
  <definition>
    <key>im_sendpoint_name_customer_account_update_note</key>
    <value><![CDATA[Zvolit, zda chcete přijímat oznámení o vašich aktualizacích účtu.]]></value>
  </definition>
  <definition>
    <key>im_customer_account_update_text_to_customer</key>
    <value><![CDATA[Váš účet byl aktualizován! Pokud jste neudělali žádné změny, obraťte se na vlastníka webu]]></value>
  </definition>
  <definition>
    <key>im_customer_account_update_email_to_customer</key>
    <value><![CDATA[Váš účet e-mailová adresa byla změněna na %s! Pokud jste neudělali tuto změnu, obraťte se na vlastníka webu]]></value>
  </definition>
  <definition>
    <key>im_customer_account_update_login_to_customer</key>
    <value><![CDATA[Váš účet přihlašovací jméno bylo změněno na %s! Pokud jste neudělali tuto změnu, obraťte se na vlastníka webu]]></value>
  </definition>
  <definition>
    <key>im_customer_account_update_password_to_customer</key>
    <value><![CDATA[Váš účet heslo bylo změněno! Pokud jste neudělali tuto změnu, obraťte se na vlastníka webu]]></value>
  </definition>
  <definition>
    <key>im_customer_contact_admin_text</key>
    <value><![CDATA[Musíš novou poptávku od zákazníka (%s %s)!]]></value>
  </definition>
  <definition>
    <key>im_sendpoint_name_newsletter</key>
    <value><![CDATA[Zpravodaje]]></value>
  </definition>
  <definition>
    <key>im_sendpoint_name_newsletter_note</key>
    <value><![CDATA[Zvolit, zda chcete dostávat oznámení o našich produktech a aktualizacích služby.]]></value>
  </definition>
  <definition>
    <key>im_product_review_text_to_admin</key>
    <value><![CDATA[Nová recenze produkt byl přidán. Zobrazit detaily # admin # rt = Katalog / revize / aktualizace a review_id = %s]]></value>
  </definition>
  <definition>
    <key>im_product_out_of_stock_admin_text</key>
    <value><![CDATA[Výrobek s ID # %s je vyprodán.]]></value>
  </definition>
</definitions>
