<?xml version="1.0" encoding="UTF-8"?>
<definitions>
  <definition>
    <key>heading_title</key>
    <value><![CDATA[Naročilo Naslov]]></value>
  </definition>
  <definition>
    <key>text_basket</key>
    <value><![CDATA[Košara]]></value>
  </definition>
  <definition>
    <key>text_shipping</key>
    <value><![CDATA[Dostava]]></value>
  </definition>
  <definition>
    <key>text_payment</key>
    <value><![CDATA[plačilo]]></value>
  </definition>
  <definition>
    <key>text_address</key>
    <value><![CDATA[naslov]]></value>
  </definition>
  <definition>
    <key>text_new_address</key>
    <value><![CDATA[nov naslov]]></value>
  </definition>
  <definition>
    <key>text_entries</key>
    <value><![CDATA[Naslov Book Entries]]></value>
  </definition>
  <definition>
    <key>entry_firstname</key>
    <value><![CDATA[Ime:]]></value>
  </definition>
  <definition>
    <key>entry_lastname</key>
    <value><![CDATA[Priimek:]]></value>
  </definition>
  <definition>
    <key>entry_company</key>
    <value><![CDATA[Podjetje:]]></value>
  </definition>
  <definition>
    <key>entry_address_1</key>
    <value><![CDATA[Naslov 1:]]></value>
  </definition>
  <definition>
    <key>entry_address_2</key>
    <value><![CDATA[Naslov 2:]]></value>
  </definition>
  <definition>
    <key>entry_postcode</key>
    <value><![CDATA[ZIP / Poštna številka:]]></value>
  </definition>
  <definition>
    <key>entry_city</key>
    <value><![CDATA[mesto:]]></value>
  </definition>
  <definition>
    <key>entry_zone</key>
    <value><![CDATA[Regija / država:]]></value>
  </definition>
  <definition>
    <key>entry_country</key>
    <value><![CDATA[Država:]]></value>
  </definition>
  <definition>
    <key>entry_telephone</key>
    <value><![CDATA[Telefon:]]></value>
  </definition>
  <definition>
    <key>entry_fax</key>
    <value><![CDATA[Fax:]]></value>
  </definition>
  <definition>
    <key>error_firstname</key>
    <value><![CDATA[Ime mora biti med 1 in 32 znakov!]]></value>
  </definition>
  <definition>
    <key>error_lastname</key>
    <value><![CDATA[Priimek mora biti med 1 in 32 znakov!]]></value>
  </definition>
  <definition>
    <key>error_address_1</key>
    <value><![CDATA[Naslov 1 mora biti med 3 in 64 znakov!]]></value>
  </definition>
  <definition>
    <key>error_city</key>
    <value><![CDATA[Mesto mora biti med 3 in 32 znakov!]]></value>
  </definition>
  <definition>
    <key>error_postcode</key>
    <value><![CDATA[Zip / poštna številka mora biti med 3 in 10 znakov!]]></value>
  </definition>
  <definition>
    <key>error_country</key>
    <value><![CDATA[Prosimo, izberite državo!]]></value>
  </definition>
  <definition>
    <key>error_zone</key>
    <value><![CDATA[Izberite regijo / državo!]]></value>
  </definition>
</definitions>
