<?xml version="1.0" encoding="UTF-8"?>
<definitions>
  <definition>
    <key>heading_title</key>
    <value><![CDATA[Produkter Kjøpt Rapporter]]></value>
  </definition>
  <definition>
    <key>column_name</key>
    <value><![CDATA[Produktnavn]]></value>
  </definition>
  <definition>
    <key>column_model</key>
    <value><![CDATA[Modell]]></value>
  </definition>
  <definition>
    <key>column_quantity</key>
    <value><![CDATA[Mengde]]></value>
  </definition>
  <definition>
    <key>column_total</key>
    <value><![CDATA[Total]]></value>
  </definition>
</definitions>
