<?xml version="1.0" encoding="UTF-8"?>
<definitions>
  <definition>
    <key>heading_title</key>
    <value><![CDATA[Ganti kata sandi]]></value>
  </definition>
  <definition>
    <key>text_account</key>
    <value><![CDATA[Rekening]]></value>
  </definition>
  <definition>
    <key>text_password</key>
    <value><![CDATA[Untuk memperbarui sandi Anda, berikan saat ini dan baru rincian sandi]]></value>
  </definition>
  <definition>
    <key>text_success</key>
    <value><![CDATA[Sukses: Kata sandi Anda telah berhasil diperbarui.]]></value>
  </definition>
  <definition>
    <key>entry_current_password</key>
    <value><![CDATA[Kata sandi saat ini:]]></value>
  </definition>
  <definition>
    <key>entry_password</key>
    <value><![CDATA[Kata sandi baru:]]></value>
  </definition>
  <definition>
    <key>entry_confirm</key>
    <value><![CDATA[Password Baru Konfirmasi:]]></value>
  </definition>
  <definition>
    <key>error_current_password</key>
    <value><![CDATA[password Anda saat ini salah! Silakan coba lagi.]]></value>
  </definition>
  <definition>
    <key>error_password</key>
    <value><![CDATA[Password harus antara 4 dan 20 karakter!]]></value>
  </definition>
  <definition>
    <key>error_confirm</key>
    <value><![CDATA[konfirmasi kata sandi tidak cocok sandi!]]></value>
  </definition>
</definitions>
